gistlicenkey/__init__.py
gistlicenkey/license.py
gistlicenkey-0.1.1.dist-info/METADATA
gistlicenkey-0.1.1.dist-info/WHEEL
gistlicenkey-0.1.1.dist-info/top_level.txt
gistlicenkey-0.1.1.dist-info/RECORD
