Metadata-Version: 2.1
Name: gistlicenkey
Version: 0.1.1
Summary: A Python wrapper for software License Key management
Home-page: https://pypi.org/project/gistlicenkey
Author: Moh Iqbal Hidayat
Author-email: iqbalmh18.dev@gmail.com
Classifier: Programming Language :: Python :: 3
Classifier: License :: OSI Approved :: MIT License
Classifier: Operating System :: OS Independent
Requires-Python: >=3.9
Requires-Dist: requests
